[
  {
    "objectID": 115534,
    "title": "Self-Portrait",
    "artist": "Käthe Kollwitz",
    "gender": "female",
    "culture": "Germany",
    "date": 1934,
    "primaryImage": "https://openaccess-cdn.clevelandart.org/1936.30/1936.30_web.jpg",
    "classification": "Print",
    "technique": "lithograph",
    "museumURL": "https://clevelandart.org/art/1936.30",
    "filename": "1936.30_web.jpg",
    "from": "Cleveland Museum of Art",
    "wall_description": null
  },
  {
    "objectID": 120761,
    "title": "Self-Portrait",
    "artist": "Käthe Kollwitz",
    "gender": "female",
    "culture": "Germany",
    "date": 1915,
    "primaryImage": "https://openaccess-cdn.clevelandart.org/1941.493/1941.493_web.jpg",
    "classification": "Print",
    "technique": "lithograph",
    "museumURL": "https://clevelandart.org/art/1941.493",
    "filename": "1941.493_web.jpg",
    "from": "Cleveland Museum of Art",
    "wall_description": null
  },
  {
    "objectID": 113311,
    "title": "Self-Portrait",
    "artist": "Käthe Kollwitz",
    "gender": "female",
    "culture": "Germany",
    "date": 1912,
    "primaryImage": "https://openaccess-cdn.clevelandart.org/1932.321/1932.321_web.jpg",
    "classification": "Print",
    "technique": "etching",
    "museumURL": "https://clevelandart.org/art/1932.321",
    "filename": "1932.321_web.jpg",
    "from": "Cleveland Museum of Art",
    "wall_description": null
  },
  {
    "objectID": 147525,
    "title": "Seated Female Nude (Self-Portrait?)",
    "artist": "Paula Modersohn-Becker",
    "gender": "female",
    "culture": "Germany",
    "date": 1899,
    "primaryImage": "https://openaccess-cdn.clevelandart.org/1973.35/1973.35_web.jpg",
    "classification": "Drawing",
    "technique": "charcoal with stumping",
    "museumURL": "https://clevelandart.org/art/1973.35",
    "filename": "1973.35_web.jpg",
    "from": "Cleveland Museum of Art",
    "wall_description": "Although Paula Modersohn-Becker died in 1907, just as the Expressionist groups in Dresden and Munich were forming, the themes of her work prefigure the movement. This likely self-portrait exhibits her desire to convey not the idealized appearance of the female body but rather its fundamental essence, stripped of all the world’s trappings. She distilled the human body into flattened forms—achieved by erasing and blending the charcoal—and abbreviated the delineation of the feet, hands, and face. The sitter’s piercing stare invites the viewer to move beyond the body as flesh and blood toward her emotional or spiritual state."
  },
  {
    "objectID": 272313,
    "title": "Self-portrait with Daughter Julie",
    "artist": "Berthe Morisot",
    "gender": "female",
    "culture": "French",
    "date": 1888,
    "primaryImage": "https://nrs.harvard.edu/urn-3:HUAM:INV178045_dynmc",
    "classification": "Prints",
    "technique": "Drypoint",
    "museumURL": "https://www.harvardartmuseums.org/collections/object/272313",
    "filename": "272313.jpg",
    "from": "Harvard Art Museum",
    "wall_description": null
  },
  {
    "objectID": 94699,
    "title": "The Balancing Act-Self-portrait (MacDowell Colony)",
    "artist": "Sandra Stark",
    "gender": "female",
    "culture": "American",
    "date": 1991,
    "primaryImage": "https://nrs.harvard.edu/urn-3:HUAM:74600_dynmc",
    "classification": "Photographs",
    "technique": "Chromogenic print",
    "museumURL": "https://www.harvardartmuseums.org/collections/object/94699",
    "filename": "94699.jpg",
    "from": "Harvard Art Museum",
    "wall_description": null
  },
  {
    "objectID": 212123,
    "title": "Self-Portrait",
    "artist": "Cecil Buller",
    "gender": "female",
    "culture": "Canadian",
    "date": 1949,
    "primaryImage": "https://nrs.harvard.edu/urn-3:HUAM:INV048546_dynmc",
    "classification": "Prints",
    "technique": "Wood engraving",
    "museumURL": "https://www.harvardartmuseums.org/collections/object/212123",
    "filename": "212123.jpg",
    "from": "Harvard Art Museum",
    "wall_description": null
  },
  {
    "objectID": 71397,
    "title": "Femme Fatale (self-portrait)",
    "artist": "Nan Goldin",
    "gender": "female",
    "culture": "American",
    "date": 1967,
    "primaryImage": "https://nrs.harvard.edu/urn-3:HUAM:756047",
    "classification": "Photographs",
    "technique": "Gelatin silver print",
    "museumURL": "https://www.harvardartmuseums.org/collections/object/71397",
    "filename": "71397.jpg",
    "from": "Harvard Art Museum",
    "wall_description": null
  },
  {
    "objectID": 258160,
    "title": "Self-Portrait",
    "artist": "Peggy Bacon",
    "gender": "female",
    "culture": "American",
    "date": 1925,
    "primaryImage": "https://nrs.harvard.edu/urn-3:HUAM:INV160272_dynmc",
    "classification": "Prints",
    "technique": "Drypoint",
    "museumURL": "https://www.harvardartmuseums.org/collections/object/258160",
    "filename": "258160.jpg",
    "from": "Harvard Art Museum",
    "wall_description": null
  },
  {
    "objectID": 348586,
    "title": "Self Portrait at Twenty Seven Years Old",
    "artist": "Gillian Wearing",
    "gender": "female",
    "culture": "British, English",
    "date": 2012,
    "primaryImage": "https://nrs.harvard.edu/urn-3:HUAM:DDC254667_dynmc",
    "classification": "Photographs",
    "technique": "Chromogenic print",
    "museumURL": "https://www.harvardartmuseums.org/collections/object/348586",
    "filename": "348586.jpg",
    "from": "Harvard Art Museum",
    "wall_description": null
  },
  {
    "objectID": 436222,
    "title": "Self-Portrait with a Harp",
    "artist": "Rose Adélaïde Ducreux",
    "gender": "female",
    "culture": "French",
    "date": 1791,
    "primaryImage": "https://images.metmuseum.org/CRDImages/ep/original/DP164843.jpg",
    "classification": "Painting",
    "technique": "Oil on canvas",
    "museumURL": "https://www.metmuseum.org/art/collection/search/436222",
    "filename": "DP164843.jpg",
    "from": "Metropolitan Museum of Art",
    "wall_description": null
  },
  {
    "objectID": 436840,
    "title": "Self-Portrait with Two Pupils, Marie Gabrielle Capet (1761–1818) and Marie Marguerite Carreaux de Rosemond (died 1788)",
    "artist": "Adélaïde Labille-Guiard",
    "gender": "female",
    "culture": "French",
    "date": 1785,
    "primaryImage": "https://images.metmuseum.org/CRDImages/ep/original/DP320103.jpg",
    "classification": "Painting",
    "technique": "Oil on canvas",
    "museumURL": "https://www.metmuseum.org/art/collection/search/436840",
    "filename": "DP320103.jpg",
    "from": "Metropolitan Museum of Art",
    "wall_description": null
  }
]